Metadata-Version: 1.1
Name: lfstool
Version: 0.1.2.dev0
Summary: A serial utility to sync local folder to Espressif ESP8266 & ESP32 chips.
Home-page: https://github.com/iotctl/lfstool
Author: Pavel Sklenar (pajikos)
Author-email: sklenar.pav@gmail.com
License: GPLv2+
Platform: UNKNOWN
Classifier: Development Status :: 5 - Production/Stable
Classifier: Intended Audience :: Developers
Classifier: Natural Language :: English
Classifier: Operating System :: POSIX
Classifier: Operating System :: MacOS :: MacOS X
Classifier: Topic :: Software Development :: Embedded Systems
Classifier: Environment :: Console
Classifier: License :: OSI Approved :: GNU General Public License v2 or later (GPLv2+)
Classifier: Programming Language :: Python :: 3.5
Classifier: Programming Language :: Python :: 3.6
Classifier: Programming Language :: Python :: 3.7
Classifier: Programming Language :: Python :: 3.8
Classifier: Programming Language :: Python :: 3.9
